pyelink/__init__.py
pyelink/audio.py
pyelink/core.py
pyelink/data.py
pyelink/events.py
pyelink/settings.py
pyelink/utils.py
pyelink/version.py
pyelink/calibration/__init__.py
pyelink/calibration/base.py
pyelink/calibration/psychopy_backend.py
pyelink/calibration/pygame_backend.py
pyelink/calibration/pyglet_backend.py
pyelink/calibration/targets.py
pyelink/display/__init__.py
pyelink/display/base.py
pyelink/display/psychopy_display.py
pyelink/display/pygame_display.py
pyelink/display/pyglet_display.py
pyelink-1.0.0.dist-info/METADATA
pyelink-1.0.0.dist-info/WHEEL
pyelink-1.0.0.dist-info/licenses/LICENSE
pyelink-1.0.0.dist-info/RECORD
