Metadata-Version: 2.4
Name: pyelink
Version: 1.0.0
Summary: Python wrapper for SR Research EyeLink eye trackers
Project-URL: Homepage, https://github.com/mh-salari/pyelink
Project-URL: Documentation, https://github.com/mh-salari/pyelink#readme
Project-URL: Repository, https://github.com/mh-salari/pyelink
Project-URL: Issues, https://github.com/mh-salari/pyelink/issues
Author-email: Mohammadhossein Salari <Mohammadhossein.salari@gmail.com>
License: MIT
License-File: LICENSE
Keywords: eyelink,eyetracking,neuroscience,psychopy,pygame,pyglet
Classifier: Development Status :: 4 - Beta
Classifier: Intended Audience :: Science/Research
Classifier: License :: OSI Approved :: MIT License
Classifier: Programming Language :: Python :: 3.9
Classifier: Programming Language :: Python :: 3.10
Classifier: Programming Language :: Python :: 3.11
Classifier: Programming Language :: Python :: 3.12
Classifier: Topic :: Scientific/Engineering
Requires-Python: >=3.9
Requires-Dist: fixation-target>=1.4.2
Requires-Dist: numpy<2.3.0,>=1.20.0
Requires-Dist: pyaudio>=0.2.14
Requires-Dist: pydantic<3.0,>=2.0
Provides-Extra: dev
Requires-Dist: ruff>=0.1.0; extra == 'dev'
Provides-Extra: psychopy
Requires-Dist: pillow>=8.0.0; extra == 'psychopy'
Requires-Dist: psychopy>=2023.1.0; (python_version < '3.12') and extra == 'psychopy'
Provides-Extra: pygame
Requires-Dist: pygame>=2.6.1; extra == 'pygame'
Provides-Extra: pyglet
Requires-Dist: pyglet>=2.1.11; extra == 'pyglet'
